{
    "type": "object",
    "properties": {
        "idMember": {
            "required": true,
            "type": "string"
        },
        "key": {
            "required": true,
            "type": "string"
        },
        "token": {
            "required": true,
            "type": "string"
        },
        "requestBody": {
            "properties": {
                "value": {
                    "description": "a string with a length from 0 to 255",
                    "type": "string"
                }
            },
            "type": "object",
            "xml": {
                "name": "member"
            }
        }
    }
}